<Properties GitUserInfo="UsingGIT" StartupConfiguration="{F34D8916-CB61-4C08-9670-2B3390C83172}|Default">
  <MonoDevelop.Ide.Workspace ActiveConfiguration="Debug" />
  <MonoDevelop.Ide.ItemProperties.Assignment FirstBuild="True" PreferredExecutionTarget="MonoDevelop.Default" />
  <MultiItemStartupConfigurations />
  <MonoDevelop.Ide.DebuggingService.Breakpoints />
  <MonoDevelop.Ide.ItemProperties.Library.Assignment FirstBuild="True" />
  <MonoDevelop.Ide.DebuggingService.PinnedWatches />
  <MonoDevelop.Ide.Workbench ActiveDocument="Assignment/Program.cs">
    <Files>
      <File FileName="Assignment1/Helpers/CourseHelper.cs" />
      <File FileName="Library.Assignment/Entities/Course.cs" />
      <File FileName="Library.Assignment/Services/CourseService.cs" />
      <File FileName="Library.Assignment/Entities/Assignment.cs" />
      <File FileName="Assignment/Program.cs" Line="1" Column="1" />
    </Files>
    <Pads>
      <Pad Id="ProjectPad">
        <State name="__root__">
          <Node name="Assignment1" expanded="True">
            <Node name="Assignment" expanded="True">
              <Node name="Helpers" expanded="True" />
            </Node>
            <Node name="Assignment1" selected="True">
              <Node name="Helpers" expanded="True" />
            </Node>
            <Node name="Library.Assignment" expanded="True">
              <Node name="Dependencies" expanded="True">
                <Node name="FrameworkReferences" expanded="True" />
              </Node>
              <Node name="Entities" expanded="True" />
              <Node name="Services" expanded="True" />
            </Node>
          </Node>
        </State>
      </Pad>
    </Pads>
  </MonoDevelop.Ide.Workbench>
</Properties>